lit/__init__.py
lit/lit.py
pytorch_zero_lit-0.2.3.dist-info/WHEEL
pytorch_zero_lit-0.2.3.dist-info/METADATA
pytorch_zero_lit-0.2.3.dist-info/RECORD
